LICENSE
MANIFEST.in
README.md
setup.py
django_skyscanner.egg-info/PKG-INFO
django_skyscanner.egg-info/SOURCES.txt
django_skyscanner.egg-info/dependency_links.txt
django_skyscanner.egg-info/pbr.json
django_skyscanner.egg-info/requires.txt
django_skyscanner.egg-info/top_level.txt
skyscannerSDK/__init__.py
skyscannerSDK/admin.py
skyscannerSDK/constants.py
skyscannerSDK/models.py
skyscannerSDK/tests.py
skyscannerSDK/utils.py
skyscannerSDK/views.py
skyscannerSDK/migrations/0001_initial.py
skyscannerSDK/migrations/0002_auto_20161008_1224.py
skyscannerSDK/migrations/__init__.py